rere.py
setup.py
rere.egg-info/PKG-INFO
rere.egg-info/SOURCES.txt
rere.egg-info/dependency_links.txt
rere.egg-info/top_level.txt