Metadata-Version: 1.0
Name: rere
Version: 0.1.0
Summary: regex redone
Home-page: https://github.com/malea/rere
Author: Malea Grubb
Author-email: maleangrubb@gmail.com
License: Apache 2
Platform: UNKNOWN
